oneqloud_polynomials/License.txt
oneqloud_polynomials/__init__.py
oneqloud_polynomials/_binary_polynomial.so
oneqloud_polynomials/binary_polynomial.py
oneqloud_polynomials-1.3.1.dist-info/METADATA
oneqloud_polynomials-1.3.1.dist-info/WHEEL
oneqloud_polynomials-1.3.1.dist-info/top_level.txt
oneqloud_polynomials-1.3.1.dist-info/RECORD
