Metadata-Version: 2.1
Name: oneqloud-polynomials
Version: 1.3.1
Summary: 1QB Information Technologies: Quadratic Binary Polynomial Library
Home-page: http://1qbit.com
Author: 1QB Information Technologies
Author-email: sdk@1qbit.com
License: Apache-2.0
Platform: UNKNOWN
Classifier: License :: OSI Approved :: Apache Software License
